trict/__init__.py
trict/trict.py
trict/util.py
trict-0.1.6.dist-info/LICENSE
trict-0.1.6.dist-info/METADATA
trict-0.1.6.dist-info/WHEEL
trict-0.1.6.dist-info/top_level.txt
trict-0.1.6.dist-info/RECORD
