Metadata-Version: 2.1
Name: trict
Version: 0.1.6
Summary: UserDict subclass with extra stuff
Home-page: https://github.com/saska/trict
Author: Saska Karsi
Author-email: saska.karsi@gmail.com
License: MIT
Keywords: mapping,map,dictionary,recursive,dict
Platform: UNKNOWN
Classifier: Development Status :: 4 - Beta
Classifier: Intended Audience :: Developers
Classifier: Topic :: Software Development :: Libraries :: Python Modules
Classifier: License :: OSI Approved :: MIT License
Classifier: Programming Language :: Python :: 3.6
Classifier: Programming Language :: Python :: 3.7
Classifier: Programming Language :: Python :: 3.8
